LICENSE
README.md
setup.py
nuovoLIRA/__init__.py
nuovoLIRA.egg-info/PKG-INFO
nuovoLIRA.egg-info/SOURCES.txt
nuovoLIRA.egg-info/dependency_links.txt
nuovoLIRA.egg-info/top_level.txt
nuovoLIRA/data/Ising_simulator.py
nuovoLIRA/data/__init__.py
nuovoLIRA/data/make_dataset.py
nuovoLIRA/features/__init__.py
nuovoLIRA/features/build_features.py
nuovoLIRA/models/__init__.py
nuovoLIRA/models/deconvolver.py
nuovoLIRA/models/predict_model.py
nuovoLIRA/models/train_model.py
nuovoLIRA/visualization/__init__.py
nuovoLIRA/visualization/visualize.py