Metadata-Version: 2.1
Name: nuovoLIRA
Version: 0.6.0
Summary: A Bayesian procedure to delineate the boundary of an extended astronomical object
Author: Brendan Martin
License: MIT
License-File: LICENSE
